b3th/__init__.py
b3th/_compat.py
b3th/cli.py
b3th/commit_message.py
b3th/config.py
b3th/conflict_resolver.py
b3th/gh_api.py
b3th/git_utils.py
b3th/llm.py
b3th/pr_description.py
b3th/stats.py
b3th/summarizer.py
b3th-0.1.3.dist-info/LICENSE
b3th-0.1.3.dist-info/METADATA
b3th-0.1.3.dist-info/WHEEL
b3th-0.1.3.dist-info/entry_points.txt
b3th-0.1.3.dist-info/RECORD
