Metadata-Version: 2.3
Name: b3th
Version: 0.1.3
Summary: CLI that auto-generates commit messages and GitHub PR descriptions
License: MIT
Keywords: git,cli,commit,pull-request,ai,groq
Author: Bethvour
Author-email: bethvourc@gmail.com
Requires-Python: >=3.9,<4.0
Classifier: License :: OSI Approved :: MIT License
Classifier: Programming Language :: Python :: 3
Classifier: Programming Language :: Python :: 3.9
Classifier: Programming Language :: Python :: 3.10
Classifier: Programming Language :: Python :: 3.11
Classifier: Programming Language :: Python :: 3.12
Classifier: Programming Language :: Python :: 3.13
Requires-Dist: click (>=8.1.4,<9)
Requires-Dist: python-dotenv (>=1.0,<2.0)
Requires-Dist: requests (>=2.32,<3.0)
Requires-Dist: typer (>=0.12,<0.13)
Project-URL: Bug Tracker, https://github.com/bethvourc/b3th/issues
Project-URL: Homepage, https://github.com/bethvourc/b3th
Project-URL: Repository, https://github.com/bethvourc/b3th
Project-URL: Source, https://github.com/bethvourc/b3th
